COERbuoy/GUI.py
COERbuoy/GUIServer.py
COERbuoy/LUT_hydro.py
COERbuoy/Parameters.py
COERbuoy/__init__.py
COERbuoy/__main__.py
COERbuoy/analyzer.py
COERbuoy/connection.py
COERbuoy/floater.py
COERbuoy/floater_BEM_LUT.py
COERbuoy/floater_LIN.py
COERbuoy/settings.txt
COERbuoy/simulation.py
COERbuoy/utils.py
COERbuoy/wavefield.py
COERbuoy/data/COERbuoy1/dynamics.py
COERbuoy/data/COERbuoy1/floater.txt
COERbuoy/data/COERbuoy1/BEM/h_-0.5_p_0/results/CA.dat
COERbuoy/data/COERbuoy1/BEM/h_-0.5_p_0/results/CM.dat
COERbuoy/data/COERbuoy1/BEM/h_-0.5_p_0/results/DiffractionForce.tec
COERbuoy/data/COERbuoy1/BEM/h_-0.5_p_0/results/ExcitationForce.tec
COERbuoy/data/COERbuoy1/BEM/h_-0.5_p_0/results/FKForce.dat
COERbuoy/data/COERbuoy1/BEM/h_-0.5_p_0/results/FKForce.tec
COERbuoy/data/COERbuoy1/BEM/h_-0.5_p_0/results/Fe.dat
COERbuoy/data/COERbuoy1/BEM/h_-0.5_p_0/results/Forces.dat
COERbuoy/data/COERbuoy1/BEM/h_-0.5_p_0/results/IRF.tec
COERbuoy/data/COERbuoy1/BEM/h_-0.5_p_0/results/RadiationCoefficients.tec
COERbuoy/data/COERbuoy1/BEM/h_-0.5_p_0/results/index.dat
COERbuoy/data/COERbuoy1/BEM/h_-1.5_p_0/results/CA.dat
COERbuoy/data/COERbuoy1/BEM/h_-1.5_p_0/results/CM.dat
COERbuoy/data/COERbuoy1/BEM/h_-1.5_p_0/results/DiffractionForce.tec
COERbuoy/data/COERbuoy1/BEM/h_-1.5_p_0/results/ExcitationForce.tec
COERbuoy/data/COERbuoy1/BEM/h_-1.5_p_0/results/FKForce.dat
COERbuoy/data/COERbuoy1/BEM/h_-1.5_p_0/results/FKForce.tec
COERbuoy/data/COERbuoy1/BEM/h_-1.5_p_0/results/Fe.dat
COERbuoy/data/COERbuoy1/BEM/h_-1.5_p_0/results/Forces.dat
COERbuoy/data/COERbuoy1/BEM/h_-1.5_p_0/results/IRF.tec
COERbuoy/data/COERbuoy1/BEM/h_-1.5_p_0/results/RadiationCoefficients.tec
COERbuoy/data/COERbuoy1/BEM/h_-1.5_p_0/results/index.dat
COERbuoy/data/COERbuoy1/BEM/h_-1_p_0/results/CA.dat
COERbuoy/data/COERbuoy1/BEM/h_-1_p_0/results/CM.dat
COERbuoy/data/COERbuoy1/BEM/h_-1_p_0/results/DiffractionForce.tec
COERbuoy/data/COERbuoy1/BEM/h_-1_p_0/results/ExcitationForce.tec
COERbuoy-0.3.6.dist-info/LICENSE.txt
COERbuoy-0.3.6.dist-info/METADATA
COERbuoy-0.3.6.dist-info/WHEEL
COERbuoy-0.3.6.dist-info/top_level.txt
COERbuoy-0.3.6.dist-info/RECORD
