Metadata-Version: 2.1
Name: COERbuoy
Version: 0.3.6
Summary: A realistic Wave Enegery Converter model to evaluate controllers
Home-page: http://coerbuoy.maynoothuniversity.ie
Author: Simon H. Thomas
Author-email: sthomas20@web.de
License: LICENSE.txt
License-File: LICENSE.txt
Requires-Dist: numpy
Requires-Dist: scipy
Requires-Dist: pandas
